README.md
setup.cfg
setup.py
massspring/Exceptions.py
massspring/__init__.py
massspring/colors.py
massspring/massspring.py
massspring/networklib.py
massspring.egg-info/PKG-INFO
massspring.egg-info/SOURCES.txt
massspring.egg-info/dependency_links.txt
massspring.egg-info/requires.txt
massspring.egg-info/top_level.txt