Metadata-Version: 2.1
Name: massspring
Version: 1.2.0
Summary: A 3D mass-spring real world simulator with more types of forces(gravity, electricity, spring, collision, ...)
Home-page: https://github.com/pooya-shams/massspring
Author: Pooya Shams kolahi
Author-email: pooya.shams.k@gmail.com
License: MIT
Download-URL: https://github.com/pooya-shams/massspring/archive/v1.2.0.tar.gz
Keywords: physics,physics-3d,physics-simulation,mass-spring,mass-spring-simulation,python
Platform: UNKNOWN
Classifier: Development Status :: 5 - Production/Stable
Classifier: Intended Audience :: Developers
Classifier: License :: OSI Approved :: MIT License
Classifier: Programming Language :: Python :: 3
Requires-Python: >=3.6
